rtl/data_memory.v
`timescale 1ns / 1ps

module data_memory (
    input  logic        clk,
    input  logic        mem_read,
    input  logic        mem_write,
    input  logic [3:0]  addr,
    input  logic [3:0]  write_data,
    output logic [3:0]  read_data
);

    logic [3:0] ram [0:15];

    // RAM khoi tao 0. Testbench se nap du lieu dau vao (preload) tuy tung chuong trinh.
    initial begin
        for (int i = 0; i < 16; i = i + 1)
            ram[i] = 4'h0;
    end

    always @(posedge clk) begin
        if (mem_write)
            ram[addr] <= write_data;
    end

    assign read_data = mem_read ? ram[addr] : 4'b0;

endmodule

rtl/alu_4bit.v
`timescale 1ns / 1ps

module alu_4bit (
    input  logic [3:0] a,
    input  logic [3:0] b,
    input  logic [2:0] op,
    output logic [3:0] result,
    output logic       zero,
    output logic       negative,
    output logic       carry
);

    always @(a, b, op) begin
        result  = 4'b0;
        carry   = 1'b0;

        case (op)
            3'b000: begin // ADD
                {carry, result} = a + b;
            end
            3'b001: begin // SUB (a - b)
                // Chuẩn hóa cờ Carry: carry = 1  -> KHÔNG mượn (a >= b)
                //                     carry = 0  -> CÓ mượn    (a < b)
                {carry, result} = {1'b0, a} + {1'b0, ~b} + 5'b00001;
            end
            3'b010: begin // AND
                result = a & b;
            end
            3'b011: begin // OR
                result = a | b;
            end
            3'b100: begin // XOR
                result = a ^ b;
            end
            3'b101: begin // INC (a + 1)
                {carry, result} = a + 1'b1;
            end
            3'b110: begin // DEC (a - 1)
                // Chuẩn hóa cờ Carry: carry = 1  -> KHÔNG mượn (a >= 1)
                //                     carry = 0  -> CÓ mượn    (a = 0)
                {carry, result} = {1'b0, a} + {1'b0, ~4'b0001} + 5'b00001;
            end
            default: begin // MOV / PASSTHRU (b)
                result = b;
            end
        endcase
    end

    assign zero     = (result == 4'b0);
    assign negative = result[3]; // MSB = sign bit trong bù 2

endmodule

rtl/register_file.v
`timescale 1ns / 1ps

module register_file (
    input  logic        clk,
    input  logic        rst_n,
    input  logic        reg_write,
    input  logic [1:0]  read_reg1,
    input  logic [1:0]  read_reg2,
    input  logic [1:0]  write_reg,
    input  logic [3:0]  write_data,
    output logic [3:0]  read_data1,
    output logic [3:0]  read_data2
);

    logic [3:0] r0, r1, r2, r3;


    always @(posedge clk or negedge rst_n) begin
        if (!rst_n) begin
            r0 <= 4'b0;
            r1 <= 4'b0;
            r2 <= 4'b0;
            r3 <= 4'b0;
        end else if (reg_write) begin
            case (write_reg)
                2'b00: r0 <= write_data;
                2'b01: r1 <= write_data;
                2'b10: r2 <= write_data;
                2'b11: r3 <= write_data;
            endcase
        end
    end

    always @(read_reg1, read_reg2, r0, r1, r2, r3) begin
        case (read_reg1)
            2'b00: read_data1 = r0;
            2'b01: read_data1 = r1;
            2'b10: read_data1 = r2;
            2'b11: read_data1 = r3;
            default: read_data1 = 4'b0;
        endcase

        case (read_reg2)
            2'b00: read_data2 = r0;
            2'b01: read_data2 = r1;
            2'b10: read_data2 = r2;
            2'b11: read_data2 = r3;
            default: read_data2 = 4'b0;
        endcase
    end

endmodule

rtl/control_unit.v
`timescale 1ns / 1ps

module control_unit (
    input  logic [3:0]  opcode,
    input  logic        zero,
    input  logic        negative,
    input  logic        imm_mode,
    output logic        reg_write,
    output logic        mem_read,
    output logic        mem_write,
    output logic        mem_to_reg,
    output logic        alu_src,
    output logic [2:0]  alu_op,
    output logic        pc_src,
    output logic [1:0]  reg_sel
);

    always @(opcode, imm_mode) begin
        // defaults
        reg_write  = 1'b0;
        mem_read   = 1'b0;
        mem_write  = 1'b0;
        mem_to_reg = 1'b0;
        alu_src    = 1'b0;
        alu_op     = 3'b000;
        reg_sel    = 2'b00;

        case (opcode)
            4'b0000: begin // NOP
                alu_op = 3'b000; // ADD (passthru)
            end
            4'b0001: begin // LOAD
                reg_write  = 1'b1;
                mem_read   = 1'b1;
                mem_to_reg = 1'b1;
                alu_src    = 1'b1; // use immediate addr
                alu_op     = 3'b000; // ADD (addr calc)
                reg_sel    = 2'b00; // R0
            end
            4'b0010: begin // STORE
                mem_write  = 1'b1;
                alu_src    = 1'b1; // use immediate addr
                alu_op     = 3'b000; // ADD (addr calc)
            end
            4'b0011: begin
                if (imm_mode) begin // LDI #imm -> load immediate into R0 (implicit)
                    reg_write  = 1'b1;
                    mem_to_reg = 1'b0;
                    alu_src    = 1'b1;    // chọn imm_val
                    alu_op     = 3'b111;  // PASSTHRU (giữ nguyên imm)
                    reg_sel    = 2'b00;   // R0 (implicit register)
                end else begin // MOV Rd, Rs (reg-reg)
                    reg_write  = 1'b1;
                    mem_to_reg = 1'b0;
                    alu_src    = 1'b0;    // chọn read_data2 (Rs)
                    alu_op     = 3'b111;  // PASSTHRU
                    reg_sel    = 2'b01;   // Rd = operand[3:2]
                end
            end
            4'b0100: begin // ADD
                reg_write  = 1'b1;
                mem_to_reg = 1'b0;
                alu_src    = 1'b0;
                alu_op     = 3'b000; // ADD
                reg_sel    = 2'b01; // Rd
            end
            4'b0101: begin // SUB
                reg_write  = 1'b1;
                mem_to_reg = 1'b0;
                alu_src    = 1'b0;
                alu_op     = 3'b001; // SUB
                reg_sel    = 2'b01; // Rd
            end
            4'b0110: begin // AND
                reg_write  = 1'b1;
                mem_to_reg = 1'b0;
                alu_src    = 1'b0;
                alu_op     = 3'b010; // AND
                reg_sel    = 2'b01; // Rd
            end
            4'b0111: begin // OR
                reg_write  = 1'b1;
                mem_to_reg = 1'b0;
                alu_src    = 1'b0;
                alu_op     = 3'b011; // OR
                reg_sel    = 2'b01; // Rd
            end
            4'b1000: begin // XOR
                reg_write  = 1'b1;
                mem_to_reg = 1'b0;
                alu_src    = 1'b0;
                alu_op     = 3'b100; // XOR
                reg_sel    = 2'b01; // Rd
            end
            4'b1001: begin // INC
                reg_write  = 1'b1;
                mem_to_reg = 1'b0;
                alu_src    = 1'b0;
                alu_op     = 3'b101; // INC
                reg_sel    = 2'b01; // Rd
            end
            4'b1010: begin // DEC
                reg_write  = 1'b1;
                mem_to_reg = 1'b0;
                alu_src    = 1'b0;
                alu_op     = 3'b110; // DEC
                reg_sel    = 2'b01; // Rd
            end
            4'b1011: begin // JMP
                // Handled continuously
            end
            4'b1100: begin // JZ
                // Handled continuously
            end
            4'b1101: begin // JN
                // Handled continuously
            end
            4'b1110: begin // OUT
                // no reg write, just output
                alu_op = 3'b000;
            end
            4'b1111: begin // HALT
                // pc_src = 0 (freeze PC by not updating in cpu_top)
            end
            default: begin
                alu_op = 3'b000;
            end
        endcase
    end

    assign pc_src = (opcode == 4'b1011) ? 1'b1 :
                    (opcode == 4'b1100) ? zero :
                    (opcode == 4'b1101) ? negative :
                    1'b0;

endmodule

rtl/instruction_memory.v
`timescale 1ns / 1ps

module instruction_memory (
    input  logic [3:0]  addr,
    output logic [8:0]  instruction
);

    logic [8:0] rom [0:15];

    // ROM khoi tao bang 0. Testbench se nap chuong trinh qua $readmemh.
    initial begin
        for (int i = 0; i < 16; i++) rom[i] = 9'h000;
    end

    assign instruction = rom[addr];

endmodule

rtl/program_counter.v
`timescale 1ns / 1ps

module program_counter (
    input  logic        clk,
    input  logic        rst_n,
    input  logic        pc_write,
    input  logic        halt,
    input  logic [3:0]  pc_next,
    output logic [3:0]  pc
);


    always @(posedge clk or negedge rst_n) begin
        if (!rst_n)
            pc <= 4'b0;
        else if (!halt && pc_write)
            pc <= pc_next;
    end

endmodule

rtl/cpu_top.v
`timescale 1ns / 1ps

module cpu_top (
    input  logic        clk,
    input  logic        rst_n,
    output logic [3:0]  out_port,
    output logic        halt_out,
    output logic [3:0]  debug_r0
);

    // PC
    logic [3:0] pc, pc_next;
    logic       pc_write;
    logic       halt;

    // Decode
    logic [3:0] opcode;
    logic [3:0] operand;
    logic       imm_mode;
    logic [3:0] imm_val;

    // Control
    logic        reg_write, mem_read, mem_write, mem_to_reg, alu_src, pc_src;
    logic [2:0]  alu_op;
    logic [1:0]  reg_sel;

    // Register File
    logic [3:0] read_data1, read_data2;
    logic [3:0] write_data;
    logic [1:0] write_reg;

    // ALU
    logic [3:0] alu_result;
    // ALU flags (combinational, from ALU each cycle)
    logic       zero, negative, carry;
    // ALU flags registered at the clock edge so branch/jump instructions
    // (JZ/JN) read the result of the *previous* executed instruction rather
    // than the (meaningless) ALU output of the branch cycle itself.
    logic       zero_r, negative_r;

    // Data Memory
    logic [3:0] mem_read_data;

    // Output register
    logic [3:0] out_reg;

    // Decoded instruction bus (9-bit). Declared explicitly to avoid
    // Icarus inferring a 1-bit scalar from the imem port connection.
    logic [8:0] instruction;

    // PC register
    program_counter pc_inst (
        .clk       (clk),
        .rst_n     (rst_n),
        .pc_write  (pc_write),
        .halt      (halt),
        .pc_next   (pc_next),
        .pc        (pc)
    );

    instruction_memory imem (
        .addr        (pc),
        .instruction (instruction)
    );

    // Decode instruction 9-bit
    //   [8]   = imm_mode (1: LDI #imm, 0: reg-reg / others)
    //   [7:4] = opcode
    //   [3:0] = operand:
    //           - MOV Rd, Rs : {Rd[3:2], Rs[1:0]}
    //           - LDI #imm   : imm[3:0] (ghi vao R0 ngam dinh, bo qua Rd)
    //           - LOAD/STORE : dia chi RAM [3:0]
    assign opcode    = instruction[7:4];
    assign operand   = instruction[3:0];
    assign imm_mode  = instruction[8];
    assign imm_val   = operand[3:0]; // imm 4-bit zero-extended (LDI)

    // Control Unit
    control_unit ctrl (
        .opcode      (opcode),
        .imm_mode    (imm_mode),
        .zero        (zero_r),
        .negative    (negative_r),
        .reg_write   (reg_write),
        .mem_read    (mem_read),
        .mem_write   (mem_write),
        .mem_to_reg  (mem_to_reg),
        .alu_src     (alu_src),
        .alu_op      (alu_op),
        .pc_src      (pc_src),
        .reg_sel     (reg_sel)
    );

    // Register file write register selection
    assign write_reg = (reg_sel == 2'b01) ? operand[3:2] : 2'b00;

    logic [1:0] read_reg1_mux;
    assign read_reg1_mux = (opcode == 4'b0010) ? 2'b00 : // STORE reads R0
                           (opcode == 4'b1110) ? operand[1:0] : // OUT reads Rs
                           operand[3:2]; // Default reads Rd

    // Register File
    register_file rf (
        .clk         (clk),
        .rst_n       (rst_n),
        .reg_write   (reg_write),
        .read_reg1   (read_reg1_mux),
        .read_reg2   (operand[1:0]),
        .write_reg   (write_reg),
        .write_data  (write_data),
        .read_data1  (read_data1),
        .read_data2  (read_data2)
    );

    // ALU input mux
    logic [3:0] alu_b;
    // alu_src=1: chon operand. Neu LDI (imm_mode) thi chon imm_val (imm 4-bit),
    //            nguoc lai chon operand (dia chi cho LOAD/STORE).
    // alu_src=0: chon read_data2 (reg-reg).
    assign alu_b = alu_src ? (imm_mode ? imm_val : operand) : read_data2;

    // ALU
    alu_4bit alu (
        .a       (read_data1),
        .b       (alu_b),
        .op      (alu_op),
        .result  (alu_result),
        .zero    (zero),
        .negative(negative),
        .carry   (carry)
    );

    // Flag register: latch ALU flags at the clock edge so that branch
    // instructions (JZ/JN) in the next cycle read the result of the
    // *previous* executed arithmetic/logic instruction, not their own
    // (meaningless) ALU output. Cleared on reset.
    always_ff @(posedge clk or negedge rst_n) begin
        if (!rst_n) begin
            zero_r    <= 1'b0;
            negative_r <= 1'b0;
        end else begin
            zero_r    <= zero;
            negative_r <= negative;
        end
    end

    // Data Memory
    data_memory dmem (
        .clk        (clk),
        .mem_read   (mem_read),
        .mem_write  (mem_write),
        .addr       (operand),
        .write_data (read_data1),
        .read_data  (mem_read_data)
    );

    // Write-back mux
    assign write_data = mem_to_reg ? mem_read_data : alu_result;

    // PC next select
    assign pc_next = pc_src ? operand : pc + 1;

    // HALT logic
    assign halt = (opcode == 4'b1111);

    // PC write enable (not on HALT)
    assign pc_write = ~halt;

    // OUT port register
    always @(posedge clk or negedge rst_n) begin
        if (!rst_n)
            out_reg <= 4'b0;
        else if (opcode == 4'b1110) // OUT
            out_reg <= read_data1;
    end

    assign out_port  = out_reg;
    assign halt_out  = halt;

    // Expose R0 for testbench inspection without hierarchical cross-module
    // references (Icarus 12.0 blocks cpu.rf.r0 access from the TB).
    // cpu_top instantiates rf directly, so rf.r0 is visible here.
    assign debug_r0 = rf.r0;

    // ---- Testbench helper tasks (keep $readmemh / RAM writes inside cpu_top) ----
    // Load a hex program into the instruction ROM.
    task load_program(input string hex_path);
        $readmemh(hex_path, imem.rom);
    endtask

    // Preload data RAM locations 10 and 11 (operands for ADD/MUL demos).
    task preload_ram(input logic [3:0] a, input logic [3:0] b);
        dmem.ram[10] = a;
        dmem.ram[11] = b;
    endtask

    // Clear data RAM locations 10 and 11.
    task clear_ram;
        dmem.ram[10] = 4'h0;
        dmem.ram[11] = 4'h0;
    endtask

endmodule

tb/tb_cpu_top.v
`timescale 1ns / 1ps

module tb_cpu_top;

    logic        clk;
    logic        rst_n;
    logic [3:0]  out_port;
    logic        halt_out;

    cpu_top uut (
        .clk      (clk),
        .rst_n    (rst_n),
        .out_port (out_port),
        .halt_out (halt_out)
    );

    // Clock generation: 10ns period
    initial clk = 0;
    always #5 clk = ~clk;

    initial begin
        $display("TB INITIAL START");
        $fflush;

        // Xuat waveform de xem bang GTKWave
        $dumpfile("cpu_top.vcd");
        $dumpvars(0, tb_cpu_top);

        rst_n = 0;
        #12;
        // Nap chuong trinh vao ROM va du lieu dau vao vao RAM TRUOC khi giai phong reset.
        // mul.asm: Mem[10]=3 (so lan), Mem[11]=4 (so cong) -> tich = 12 = 0xC.
        uut.load_program("sim/mul.hex");
        uut.preload_ram(4'd3, 4'd4);
        rst_n = 1;

        // MUL loop = 3 vong lap x 5 lenh ~ 23 chu ky; chay 60 cho du phong.
        repeat (60) @(posedge clk);

        // Kiem tra ket qua truc tiep tu bo nho du lieu
        // Chuong trinh: Mem[10]=3, Mem[11]=4 -> tich 12 luu Mem[12]
        $display("Simulation finished:");
        $display("  out_port = %d (0x%h)", out_port, out_port);
        $display("  halt_out = %b", halt_out);
        $display("  Mem[12]  = %d (0x%h) [expected 12]",
                  uut.dmem.ram[12], uut.dmem.ram[12]);

        if (out_port == 4'd12 && uut.dmem.ram[12] == 4'd12) begin
            $display("TEST PASSED: OUT = 12, Mem[12] = 12 as expected");
        end else begin
            $error("TEST FAILED: OUT = %d, Mem[12] = %d, expected 12",
                    out_port, uut.dmem.ram[12]);
        end

        $finish;
    end

    // Monitor tung chu ky de hieu single-cycle datapath
    always @(posedge clk) begin
        $display("Time=%0t | PC=%d | Opcode=%b | Operand=%b | R0=%d R1=%d R2=%d R3=%d | OUT=%d | HALT=%b",
                 $time, uut.pc, uut.opcode, uut.operand,
                 uut.rf.r0, uut.rf.r1, uut.rf.r2, uut.rf.r3,
                 out_port, halt_out);
    end

endmodule

cpu_top.vcd
$date
	Fri Jul 17 13:29:47 2026
$end
$version
	Icarus Verilog
$end
$timescale
	1ps
$end
$scope module tb_cpu_top $end
$var wire 4 ! out_port [3:0] $end
$var wire 1 " halt_out $end
$var reg 1 # clk $end
$var reg 1 $ rst_n $end
$scope module uut $end
$var wire 1 # clk $end
$var wire 4 % debug_r0 [3:0] $end
$var wire 1 " halt_out $end
$var wire 4 & imm_val [3:0] $end
$var wire 4 ' out_port [3:0] $end
$var wire 1 ( pc_write $end
$var wire 1 $ rst_n $end
$var wire 1 ) zero $end
$var wire 2 * write_reg [1:0] $end
$var wire 4 + write_data [3:0] $end
$var wire 1 , reg_write $end
$var wire 2 - reg_sel [1:0] $end
$var wire 2 . read_reg1_mux [1:0] $end
$var wire 4 / read_data2 [3:0] $end
$var wire 4 0 read_data1 [3:0] $end
$var wire 1 1 pc_src $end
$var wire 4 2 pc_next [3:0] $end
$var wire 4 3 pc [3:0] $end
$var wire 4 4 operand [3:0] $end
$var wire 4 5 opcode [3:0] $end
$var wire 1 6 negative $end
$var wire 1 7 mem_write $end
$var wire 1 8 mem_to_reg $end
$var wire 4 9 mem_read_data [3:0] $end
$var wire 1 : mem_read $end
$var wire 9 ; instruction [8:0] $end
$var wire 1 < imm_mode $end
$var wire 1 = halt $end
$var wire 1 > carry $end
$var wire 1 ? alu_src $end
$var wire 4 @ alu_result [3:0] $end
$var wire 3 A alu_op [2:0] $end
$var wire 4 B alu_b [3:0] $end
$var reg 1 C negative_r $end
$var reg 4 D out_reg [3:0] $end
$var reg 1 E zero_r $end
$scope module alu $end
$var wire 4 F b [3:0] $end
$var wire 1 ) zero $end
$var wire 3 G op [2:0] $end
$var wire 1 6 negative $end
$var wire 4 H a [3:0] $end
$var reg 1 > carry $end
$var reg 4 I result [3:0] $end
$upscope $end
$scope module ctrl $end
$var wire 1 < imm_mode $end
$var wire 1 C negative $end
$var wire 4 J opcode [3:0] $end
$var wire 1 E zero $end
$var wire 1 1 pc_src $end
$var reg 3 K alu_op [2:0] $end
$var reg 1 ? alu_src $end
$var reg 1 : mem_read $end
$var reg 1 8 mem_to_reg $end
$var reg 1 7 mem_write $end
$var reg 2 L reg_sel [1:0] $end
$var reg 1 , reg_write $end
$upscope $end
$scope module dmem $end
$var wire 4 M addr [3:0] $end
$var wire 1 # clk $end
$var wire 1 : mem_read $end
$var wire 1 7 mem_write $end
$var wire 4 N write_data [3:0] $end
$var wire 4 O read_data [3:0] $end
$scope begin $ivl_for_loop0 $end
$var integer 32 P i [31:0] $end
$upscope $end
$upscope $end
$scope module imem $end
$var wire 9 Q instruction [8:0] $end
$var wire 4 R addr [3:0] $end
$scope begin $ivl_for_loop1 $end
$var integer 32 S i [31:0] $end
$upscope $end
$upscope $end
$scope module pc_inst $end
$var wire 1 # clk $end
$var wire 1 = halt $end
$var wire 4 T pc_next [3:0] $end
$var wire 1 ( pc_write $end
$var wire 1 $ rst_n $end
$var reg 4 U pc [3:0] $end
$upscope $end
$scope module rf $end
$var wire 1 # clk $end
$var wire 2 V read_reg1 [1:0] $end
$var wire 2 W read_reg2 [1:0] $end
$var wire 1 , reg_write $end
$var wire 1 $ rst_n $end
$var wire 4 X write_data [3:0] $end
$var wire 2 Y write_reg [1:0] $end
$var reg 4 Z r0 [3:0] $end
$var reg 4 [ r1 [3:0] $end
$var reg 4 \ r2 [3:0] $end
$var reg 4 ] r3 [3:0] $end
$var reg 4 ^ read_data1 [3:0] $end
$var reg 4 _ read_data2 [3:0] $end
$upscope $end
$scope task clear_ram $end
$upscope $end
$scope task load_program $end
$upscope $end
$scope task preload_ram $end
$var reg 4 ` a [3:0] $end
$var reg 4 a b [3:0] $end
$upscope $end
$upscope $end
$upscope $end
$enddefinitions $end
$comment Show the parameter values. $end
$dumpall
$end
#0
$dumpvars
bx a
bx `
b0 _
b0 ^
b0 ]
b0 \
b0 [
b0 Z
b0 Y
b0 X
b0 W
b0 V
b0 U
b1 T
b10000 S
b0 R
b0 Q
b10000 P
b0 O
b0 N
b0 M
b0 L
b0 K
b0 J
b0 I
b0 H
b0 G
b0 F
0E
b0 D
0C
b0 B
b0 A
b0 @
0?
0>
0=
0<
b0 ;
0:
b0 9
08
07
06
b0 5
b0 4
b0 3
b1 2
01
b0 0
b0 /
b0 .
b0 -
0,
b0 +
b0 *
1)
1(
b0 '
b0 &
b0 %
0$
0#
0"
b0 !
$end
#5000
1#
#10000
0#
#12000
16
b10 .
b10 V
0)
b1010 @
b1010 I
b1010 B
b1010 F
b11 +
b11 X
b11 9
b11 O
b10 W
1?
18
1:
1,
b1010 &
b1010 4
b1010 M
b1 5
b1 J
1$
b100 a
b11 `
b11010 ;
b11010 Q
#15000
b1 .
b1 V
06
b11 /
b11 _
b1 *
b1 Y
0)
b11 @
b11 I
b11 B
b11 F
b11 +
b11 X
b0 W
b0 9
b0 O
b1 -
b1 L
b111 A
b111 G
b111 K
0?
08
0:
1,
b100 &
b100 4
b100 M
b11 5
b11 J
b10 2
b10 T
b110100 ;
b110100 Q
b1 3
b1 R
b1 U
b11 %
b11 Z
1C
1#
#20000
0#
#25000
16
b10 .
b10 V
b0 /
b0 _
b1011 B
b1011 F
b100 +
b100 X
b100 9
b100 O
b0 *
b0 Y
0)
b1011 @
b1011 I
b11 W
1?
18
1:
b0 -
b0 L
b0 A
b0 G
b0 K
1,
b0 0
b0 H
b0 N
b0 ^
b1011 &
b1011 4
b1011 M
b1 5
b1 J
b11 2
b11 T
0C
b11 [
b11011 ;
b11011 Q
b10 3
b10 R
b10 U
1#
#30000
0#
#35000
b11 .
b11 V
06
b100 /
b100 _
b11 *
b11 Y
0)
b100 @
b100 I
b100 B
b100 F
b100 +
b100 X
b0 W
b0 9
b0 O
b1 -
b1 L
b111 A
b111 G
b111 K
0?
08
0:
1,
b1100 &
b1100 4
b1100 M
b11 5
b11 J
b100 2
b100 T
b111100 ;
b111100 Q
b11 3
b11 R
b11 U
b100 %
b100 Z
1C
1#
#40000
0#
#45000
b0 +
b0 X
b0 .
b0 V
b0 B
b0 F
b0 *
b0 Y
1)
b0 @
b0 I
1?
b0 -
b0 L
b111 A
b111 G
b111 K
1,
b100 0
b100 H
b100 N
b100 ^
1<
b0 &
b0 4
b0 M
b101 2
b101 T
0C
b100 ]
b100110000 ;
b100110000 Q
b100 3
b100 R
b100 U
1#
#50000
0#
#55000
b10 .
b10 V
b10 *
b10 Y
b1 -
b1 L
b111 A
b111 G
b111 K
0?
1,
0<
b1000 &
b1000 4
b1000 M
b110 2
b110 T
b0 /
b0 _
b0 0
b0 H
b0 N
b0 ^
b111000 ;
b111000 Q
b101 3
b101 R
b101 U
b0 %
b0 Z
1E
1#
#60000
0#
#65000
b100 +
b100 X
0)
b100 @
b100 I
b100 B
b100 F
b100 /
b100 _
b11 W
b1 -
b1 L
b0 A
b0 G
b0 K
1,
b1011 &
b1011 4
b1011 M
b100 5
b100 J
b111 2
b111 T
b1001011 ;
b1001011 Q
b110 3
b110 R
b110 U
1#
#70000
0#
#75000
b1 .
b1 V
b0 B
b0 F
b0 /
b0 _
1>
b1 *
b1 Y
06
b10 +
b10 X
b0 W
b110 A
b110 G
b110 K
b1 -
b1 L
1,
0)
b10 @
b10 I
b100 &
b100 4
b100 M
b1010 5
b1010 J
b1000 2
b1000 T
b11 0
b11 H
b11 N
b11 ^
b10100100 ;
b10100100 Q
b111 3
b111 R
b111 U
b100 \
0E
1#
#80000
0#
#85000
16
b1000 +
b1000 X
b10 .
b10 V
b100 B
b100 F
b100 /
b100 _
b0 *
b0 Y
0>
0)
b1000 @
b1000 I
b10 W
b0 -
b0 L
b0 A
b0 G
b0 K
0,
b100 0
b100 H
b100 N
b100 ^
b1010 &
b1010 4
b1010 M
b1100 5
b1100 J
b1001 2
b1001 T
b10 [
b11001010 ;
b11001010 Q
b1000 3
b1000 R
b1000 U
1#
#90000
0#
#95000
06
b110 +
b110 X
0)
b110 @
b110 I
b10 0
b10 H
b10 N
b10 ^
b1 .
b1 V
11
b110 &
b110 4
b110 M
b1011 5
b1011 J
b110 2
b110 T
b10110110 ;
b10110110 Q
b1001 3
b1001 R
b1001 U
1C
1#
#100000
0#
#105000
16
b1000 +
b1000 X
0)
b1000 @
b1000 I
b100 0
b100 H
b100 N
b100 ^
b10 .
b10 V
b10 *
b10 Y
b11 W
b111 2
b111 T
b1 -
b1 L
1,
01
b1011 &
b1011 4
b1011 M
b100 5
b100 J
0C
b1001011 ;
b1001011 Q
b110 3
b110 R
b110 U
1#
#110000
0#
#115000
b1 .
b1 V
b0 B
b0 F
06
b0 /
b0 _
1>
b1 *
b1 Y
b1 +
b1 X
b0 W
b110 A
b110 G
b110 K
b1 -
b1 L
1,
0)
b1 @
b1 I
b100 &
b100 4
b100 M
b1010 5
b1010 J
b1000 2
b1000 T
b10 0
b10 H
b10 N
b10 ^
b10100100 ;
b10100100 Q
b111 3
b111 R
b111 U
b1000 \
1C
1#
#120000
0#
#125000
06
b0 +
b0 X
b10 .
b10 V
b1000 B
b1000 F
b1000 /
b1000 _
b0 *
b0 Y
1>
1)
b0 @
b0 I
b10 W
b0 -
b0 L
b0 A
b0 G
b0 K
0,
b1000 0
b1000 H
b1000 N
b1000 ^
b1010 &
b1010 4
b1010 M
b1100 5
b1100 J
b1001 2
b1001 T
0C
b1 [
b11001010 ;
b11001010 Q
b1000 3
b1000 R
b1000 U
1#
#130000
0#
#135000
16
b1001 +
b1001 X
0)
b1001 @
b1001 I
0>
b1 0
b1 H
b1 N
b1 ^
b1 .
b1 V
11
b110 &
b110 4
b110 M
b1011 5
b1011 J
b110 2
b110 T
b10110110 ;
b10110110 Q
b1001 3
b1001 R
b1001 U
1E
1#
#140000
0#
#145000
16
b1100 +
b1100 X
b1000 0
b1000 H
b1000 N
b1000 ^
0)
b1100 @
b1100 I
b10 .
b10 V
b100 B
b100 F
b100 /
b100 _
b10 *
b10 Y
b11 W
b111 2
b111 T
b1 -
b1 L
1,
01
b1011 &
b1011 4
b1011 M
b100 5
b100 J
1C
0E
b1001011 ;
b1001011 Q
b110 3
b110 R
b110 U
1#
#150000
0#
#155000
b1 .
b1 V
b0 B
b0 F
b0 /
b0 _
b1 *
b1 Y
06
b0 +
b0 X
b0 W
b110 A
b110 G
b110 K
b1 -
b1 L
1,
1>
1)
b0 @
b0 I
b100 &
b100 4
b100 M
b1010 5
b1010 J
b1000 2
b1000 T
b1 0
b1 H
b1 N
b1 ^
b10100100 ;
b10100100 Q
b111 3
b111 R
b111 U
b1100 \
1#
#160000
0#
#165000
16
b1000 +
b1000 X
0)
b1000 @
b1000 I
b10 .
b10 V
b1100 B
b1100 F
b1100 /
b1100 _
b0 *
b0 Y
11
1>
b10 W
b0 -
b0 L
b0 A
b0 G
b0 K
0,
b1100 0
b1100 H
b1100 N
b1100 ^
b1010 &
b1010 4
b1010 M
b1100 5
b1100 J
b1010 2
b1010 T
0C
1E
b0 [
b11001010 ;
b11001010 Q
b1000 3
b1000 R
b1000 U
1#
#170000
0#
#175000
b0 0
b0 H
b0 N
b0 ^
b0 .
b0 V
b1100 +
b1100 X
0>
0)
b1100 @
b1100 I
b1011 2
b1011 T
b1 -
b1 L
b111 A
b111 G
b111 K
1,
01
b10 &
b10 4
b10 M
b11 5
b11 J
b110010 ;
b110010 Q
b1010 3
b1010 R
b1010 U
1C
0E
1#
#180000
0#
#185000
b1000 +
b1000 X
1>
0)
b1000 @
b1000 I
b0 W
1?
17
b0 -
b0 L
b0 A
b0 G
b0 K
0,
b1100 0
b1100 H
b1100 N
b1100 ^
b1100 &
b1100 4
b1100 M
b10 5
b10 J
b1100 2
b1100 T
b1100 %
b1100 Z
b101100 ;
b101100 Q
b1011 3
b1011 R
b1011 U
1#
#190000
0#
#195000
0?
07
b0 &
b0 4
b0 M
b1110 5
b1110 J
b1101 2
b1101 T
b11100000 ;
b11100000 Q
b1100 3
b1100 R
b1100 U
1#
#200000
0#
#205000
0(
1"
1=
b1111 5
b1111 J
b1110 2
b1110 T
b1100 !
b1100 '
b1100 D
b11110000 ;
b11110000 Q
b1101 3
b1101 R
b1101 U
1#
